zhmiscellany/__init__.py
zhmiscellany/_discord_supportfuncs.py
zhmiscellany/_fileio_supportfuncs.py
zhmiscellany/_misc_supportfuncs.py
zhmiscellany/_processing_supportfuncs.py
zhmiscellany/_py_resources.py
zhmiscellany/_resource_files_lookup.py
zhmiscellany/cpp.py
zhmiscellany/dict.py
zhmiscellany/discord.py
zhmiscellany/fileio.py
zhmiscellany/gui.py
zhmiscellany/image.py
zhmiscellany/list.py
zhmiscellany/macro.py
zhmiscellany/math.py
zhmiscellany/misc.py
zhmiscellany/netio.py
zhmiscellany/pastebin.py
zhmiscellany/pipes.py
zhmiscellany/processing.py
zhmiscellany/rust.py
zhmiscellany/string.py
zhmiscellany-6.2.3.dist-info/METADATA
zhmiscellany-6.2.3.dist-info/WHEEL
zhmiscellany-6.2.3.dist-info/top_level.txt
zhmiscellany-6.2.3.dist-info/RECORD
