Metadata-Version: 2.1
Name: zhmiscellany
Version: 6.2.3
Summary: A collection of useful/interesting python libraries made by zh.
Home-page: https://discord.gg/ThBBAuueVJ
Author: zh
Author-email: imnotgivingmyemailjustaddmeondiscordmydiscordisz_h_@zh.com
Project-URL: Bug Tracker, https://github.com/zen-ham/zhmiscellany/issues
Classifier: Programming Language :: Python :: 3
Classifier: Operating System :: Microsoft :: Windows
Requires-Python: >=3.6
Requires-Dist: ray>=0
Requires-Dist: pycryptodome>=0
Requires-Dist: discum==1.1.0
Requires-Dist: requests>=0
Requires-Dist: dill>=0
Requires-Dist: numpy>=0
Requires-Dist: keyboard>=0
Requires-Dist: psutil>=0
Requires-Dist: kthread>=0
Requires-Dist: pillow>=0
Requires-Dist: fuzzywuzzy>=0
Requires-Dist: orjson>=0
Requires-Dist: pyautogui>=0; sys_platform == "linux"
Requires-Dist: pywin32>=0; sys_platform == "win32"
Requires-Dist: random-header-generator>=0; sys_platform == "win32"
Requires-Dist: pydirectinput>=0; sys_platform == "win32"
